Adafruit_PN532-1.2.1.dist-info/metadata.json
Adafruit_PN532-1.2.1.dist-info/METADATA
Adafruit_PN532-1.2.1.dist-info/RECORD
Adafruit_PN532-1.2.1.dist-info/WHEEL
Adafruit_PN532-1.2.1.dist-info/DESCRIPTION.rst
Adafruit_PN532-1.2.1.dist-info/dependency_links.txt
Adafruit_PN532-1.2.1.dist-info/top_level.txt
Adafruit_PN532/PN532.py
Adafruit_PN532/__init__.py
