Metadata-Version: 1.1
Name: Adafruit_PN532
Version: 1.2.1
Summary: Python library for accessing a PN532 NFC breakout over a SPI connection from a Raspberry Pi, BeagleBone Black, etc.
Home-page: https://github.com/adafruit/Adafruit_Python_PN532/
Author: Tony DiCola
Author-email: tdicola@adafruit.com
License: MIT
Platform: UNKNOWN
Classifier: Development Status :: 4 - Beta
Classifier: Operating System :: POSIX :: Linux
Classifier: License :: OSI Approved :: MIT License
Classifier: Intended Audience :: Developers
Classifier: Programming Language :: Python :: 2.7
Classifier: Programming Language :: Python :: 3
Classifier: Topic :: Software Development
Classifier: Topic :: System :: Hardware
